zenity.py
Zenity-2.0.0.data/scripts/zenity.py
Zenity-2.0.0.dist-info/LICENSE
Zenity-2.0.0.dist-info/METADATA
Zenity-2.0.0.dist-info/WHEEL
Zenity-2.0.0.dist-info/entry_points.txt
Zenity-2.0.0.dist-info/top_level.txt
Zenity-2.0.0.dist-info/zip-safe
Zenity-2.0.0.dist-info/RECORD
