Metadata-Version: 1.1
Name: Zenity
Version: 2.0.0
Summary: lightweight and full featured library to display dialogs with python.
Home-page: https://github.com/Ksengine/Zenity
Author: Kavindu Santhusa
Author-email: kavindusanthusa@gmail.com
License: MIT
Download-URL: https://pypi.python.org/pypi/Zenity
Keywords: GUI,dialog,lightweight,full,featured,full-featured,library,to,display dialogs,display dialog,dialogs,python
Platform: any
Classifier: Intended Audience :: Developers
Classifier: Development Status :: 4 - Beta
Classifier: Operating System :: OS Independent
Classifier: License :: OSI Approved :: MIT License
Classifier: Operating System :: MacOS :: MacOS X
Classifier: Operating System :: Microsoft :: Windows
Classifier: Operating System :: POSIX
Classifier: Programming Language :: Python
Classifier: Programming Language :: Python :: 2.7
Classifier: Programming Language :: Python :: 3.4
Classifier: Programming Language :: Python :: 3.5
Classifier: Programming Language :: Python :: 3.6
Classifier: Programming Language :: Python :: 3.7
Classifier: Programming Language :: Python :: 3
Provides: Zenity
